packerpy
