Metadata-Version: 1.1
Name: packer.py
Version: 0.2.0
Summary: packer.py - python library for interacting with hashicorp packer CLI
Home-page: https://github.com/mayn/packer.py
Author: Matthew Aynalem
Author-email: maynalem@gmail.com
License: Apache License 2.0
Keywords: hashicorp packer
Platform: UNKNOWN
Classifier: License :: OSI Approved :: Apache Software License
Classifier: Programming Language :: Python :: 2
Classifier: Programming Language :: Python :: 2.7
Classifier: Programming Language :: Python :: 3
Classifier: Programming Language :: Python :: 3.4
Classifier: Programming Language :: Python :: 3.5
Classifier: Programming Language :: Python :: 3.6
